{
  "Dt": 28,
  "HM": 15,
  "A2": 3,
  "BM": 127,
  "Maschio": 98,
  "Sinceramente": 133,
  "Movimento Lento": 16,
  "Houseparty": 2,
  "Mon Amour": 6,
  "Il Mondo Prima Di Te": 3,
  "Storie Brevi": 45,
  "everything i wanted": 249,
  "[BP] Voila": 80,
  "[EK] Voila": 15,
  "Tell": 129,
  "Bad Memories": 2,
  "[BE] No Time to Die": 15,
  "Maison": 169,
  "Supereroi": 1,
  "Indaco Violento": 33,
  "A": 3,
  "Paradise": 77,
  "SYL": 67,
  "Set Fire to the Rain": 3,
  "Per Te": 190,
  "POYH": 9,
  "Symphony": 1,
  "Dream": 1,
  "Your Power": 12,
  "OMW": 30,
  "Six Feet Under": 13,
  "bury a friend": 78,
  "Where Are You Now": 39,
  "LC": 1,
  "when the party's over": 40,
  "Buon Viaggio": 5,
  "Ce Monde": 131,
  "Ovunque Sarai": 110,
  "lovely": 478,
  "AL": 21,
  "Dancin": 478,
  "[L] Voila": 170,
  "Stay True": 250,
  "Next to Me": 48,
  "Cuore di Latta": 8,
  "L'Amour Toujours": 253,
  "Broken Strings": 17,
  "Hero": 148,
  "Down": 133,
  "Lifeline": 39,
  "Jamais": 137,
  "In The End": 106,
  "Not Home": 36,
  "DYWC": 155,
  "Good Life": 3,
  "Tous Les Mêmes": 159,
  "Starboy": 93,
  "Apologize": 27,
  "To Build a Home": 16,
  "Scared to be Lonely": 21,
  "Circles": 39,
  "Pompeii": 78,
  "Hold On": 61,
  "Hollywood's Bleeding": 192,
  "Idea 22 Remix": 247,
  "glow in the dark": 216,
  "Stranger Things": 939,
  "Ordinary": 26,
  "La symphonie des éclairs": 1001,
  "Barcelona": 19,
  "Unsure": 280,
  "Therefore I Am": 118,
  "go to hell": 253,
  "bellyache": 156,
  "BLUE": 85,
  "BITTERSUITE": 48,
  "CHIHIRO": 464,
  "Lo Vas A Olvidar": 124,
  "Just Wanna Know": 129,
  "idontwannabeyouanymore": 201,
  "Wait": 62
}